.bumpversion.cfg
CONTRIBUTING.md
LICENSE
MANIFEST.in
Makefile
README.md
mkdocs.yml
pyproject.toml
setup.py
docs/contributing.md
docs/gen_ref_pages.py
docs/index.md
docs/license.md
docs/examples/example1.ipynb
docs/examples/example1.md
docs/examples/index.md
sec_web_scraper/Downloader.py
sec_web_scraper/Scraper.py
sec_web_scraper/__init__.py
sec_web_scraper/__main__.py
sec_web_scraper/_version.py
sec_web_scraper.egg-info/PKG-INFO
sec_web_scraper.egg-info/SOURCES.txt
sec_web_scraper.egg-info/dependency_links.txt
sec_web_scraper.egg-info/requires.txt
sec_web_scraper.egg-info/top_level.txt
sec_web_scraper/tests/__init__.py
sec_web_scraper/tests/test_all.py
sec_web_scraper/tests/test_downloader.py