Metadata-Version: 2.1
Name: sec-web-scraper
Version: 0.1.1
Summary: SEC Web Scraper for the EDGAR API
Author-email: Deji  <deji725@gmail.com>
License: MIT License
Project-URL: repository, https://github.com/deji725/sec-web-scraper
Platform: UNKNOWN
Classifier: Development Status :: 2 - Pre-Alpha
Classifier: Programming Language :: Python :: Implementation :: CPython
Classifier: Programming Language :: Python :: Implementation :: PyPy
Classifier: Programming Language :: Python :: 3
Classifier: Programming Language :: Python :: 3.7
Classifier: Programming Language :: Python :: 3.8
Classifier: Programming Language :: Python :: 3.9
Classifier: Programming Language :: Python :: 3.10
Classifier: Programming Language :: Python :: 3.11
Requires-Python: >=3.7
Provides-Extra: develop
Provides-Extra: docs
License-File: LICENSE
